Mopidy_Emby-0.2.6.dist-info/DESCRIPTION.rst
Mopidy_Emby-0.2.6.dist-info/METADATA
Mopidy_Emby-0.2.6.dist-info/RECORD
Mopidy_Emby-0.2.6.dist-info/WHEEL
Mopidy_Emby-0.2.6.dist-info/entry_points.txt
Mopidy_Emby-0.2.6.dist-info/metadata.json
Mopidy_Emby-0.2.6.dist-info/top_level.txt
mopidy_emby/__init__.py
mopidy_emby/backend.py
mopidy_emby/ext.conf
mopidy_emby/library.py
mopidy_emby/playback.py
mopidy_emby/remote.py
mopidy_emby/utils.py
