Metadata-Version: 2.0
Name: Mopidy-Emby
Version: 0.2.6
Summary: Mopidy extension for playing music from Emby
Home-page: https://github.com/xsteadfastx/mopidy-emby
Author: Marvin Steadfast
Author-email: marvin@xsteadfastx.org
License: Apache License, Version 2.0
Platform: UNKNOWN
Classifier: Environment :: No Input/Output (Daemon)
Classifier: Intended Audience :: End Users/Desktop
Classifier: License :: OSI Approved :: Apache Software License
Classifier: Operating System :: OS Independent
Classifier: Programming Language :: Python :: 2
Classifier: Topic :: Multimedia :: Sound/Audio :: Players
Requires-Dist: Mopidy (>=1.0)
Requires-Dist: Pykka (>=1.1)
Requires-Dist: requests (>=2.0)
Requires-Dist: setuptools
